{
  "gitSyncId": "6694e79242e0cf1ce121987e_67e76992-5686-40b5-904b-7445344e2d0e",
  "id": "HomePage_globalData.setEventDialogData",
  "pluginId": "js-plugin",
  "pluginType": "JS",
  "unpublishedAction": {
    "actionConfiguration": {
      "encodeParamsToggle": true,
      "jsArguments": [
        {
          "name": "data"
        }
      ],
      "paginationType": "NONE",
      "timeoutInMillisecond": 10000
    },
    "collectionId": "HomePage_globalData",
    "confirmBeforeExecute": false,
    "datasource": {
      "isAutoGenerated": false,
      "name": "UNUSED_DATASOURCE",
      "pluginId": "js-plugin"
    },
    "dynamicBindingPathList": [
      {
        "key": "body"
      }
    ],
    "executeOnLoad": false,
    "fullyQualifiedName": "globalData.setEventDialogData",
    "name": "setEventDialogData",
    "pageId": "HomePage",
    "userSetOnLoad": false
  }
}