{
  "accentColor": "{{appsmith.theme.colors.primaryColor}}",
  "animateLoading": true,
  "borderRadius": "{{appsmith.theme.borderRadius.appBorderRadius}}",
  "bottomRow": 17,
  "boxShadow": "none",
  "closeOnSelection": true,
  "dateFormat": "LL",
  "datePickerType": "DATE_PICKER",
  "defaultDate": "2024-08-06T08:24:21.765Z",
  "displayName": "DatePicker",
  "dynamicBindingPathList": [
    {
      "key": "accentColor"
    },
    {
      "key": "borderRadius"
    }
  ],
  "dynamicHeight": "FIXED",
  "dynamicTriggerPathList": [],
  "firstDayOfWeek": 0,
  "hideCard": false,
  "iconSVG": "/static/media/icon.4c94d9b859c11557d7a5d801df99e8d5.svg",
  "isDeprecated": false,
  "isDisabled": false,
  "isLoading": false,
  "isRequired": false,
  "isVisible": true,
  "key": "ng6iqxj9xu",
  "label": "Label",
  "labelAlignment": "left",
  "labelPosition": "Top",
  "labelTextColor": "#ef4444",
  "labelTextSize": "0.875rem",
  "labelWidth": 5,
  "leftColumn": 0,
  "maxDate": "2121-12-31T18:29:00.000Z",
  "maxDynamicHeight": 9000,
  "minDate": "1920-12-31T18:30:00.000Z",
  "minDynamicHeight": 4,
  "minWidth": 450,
  "mobileBottomRow": 25,
  "mobileLeftColumn": 0,
  "mobileRightColumn": 19,
  "mobileTopRow": 18,
  "needsErrorInfo": false,
  "onCanvasUI": {
    "disableParentSelection": false,
    "focusBGCSSVar": "--on-canvas-ui-widget-focus",
    "focusColorCSSVar": "--on-canvas-ui-widget-selection",
    "selectionBGCSSVar": "--on-canvas-ui-widget-selection",
    "selectionColorCSSVar": "--on-canvas-ui-widget-focus"
  },
  "originalBottomRow": 17,
  "originalTopRow": 10,
  "parentColumnSpace": 19.234375,
  "parentId": "0",
  "parentRowSpace": 10,
  "renderMode": "CANVAS",
  "responsiveBehavior": "fill",
  "rightColumn": 8,
  "searchTags": [
    "calendar"
  ],
  "shortcuts": false,
  "tags": [
    "输入框"
  ],
  "thumbnailSVG": "/static/media/thumbnail.6f2ddea04e74f31810326bef3bc239b8.svg",
  "timePrecision": "minute",
  "topRow": 10,
  "type": "DATE_PICKER_WIDGET2",
  "version": 2,
  "widgetId": "8dje68avql",
  "widgetName": "DatePicker1"
}