{
  "gitSyncId": "6694e79242e0cf1ce121987e_3f1091bf-7d6b-4367-a7d2-fad75b672682",
  "id": "HomePage_globalData.getVideosUrlList",
  "pluginId": "js-plugin",
  "pluginType": "JS",
  "unpublishedAction": {
    "actionConfiguration": {
      "encodeParamsToggle": true,
      "jsArguments": [
        {
          "name": "points"
        }
      ],
      "paginationType": "NONE",
      "timeoutInMillisecond": 10000
    },
    "collectionId": "HomePage_globalData",
    "confirmBeforeExecute": false,
    "datasource": {
      "isAutoGenerated": false,
      "name": "UNUSED_DATASOURCE",
      "pluginId": "js-plugin"
    },
    "dynamicBindingPathList": [
      {
        "key": "body"
      }
    ],
    "executeOnLoad": false,
    "fullyQualifiedName": "globalData.getVideosUrlList",
    "name": "getVideosUrlList",
    "pageId": "HomePage",
    "userSetOnLoad": false
  }
}